{"efiscoi.sefaz.pe.gov.br":{"/":{"JSESSIONID":{"key":"JSESSIONID","value":"7bPR_cRqWOxhjzd3VuxA6jxxsBdHnRndq7jNoExq.ocp-7d5kk-worker-85xbx","domain":"efiscoi.sefaz.pe.gov.br","path":"/","hostOnly":true,"creation":"2026-01-23T06:39:40.267Z","lastAccessed":"2026-01-23T06:39:40.267Z"},"session-cookie":{"key":"session-cookie","value":"\"f795cce0a99524d4\"","domain":"efiscoi.sefaz.pe.gov.br","path":"/","httpOnly":true,"hostOnly":true,"creation":"2026-01-23T06:39:40.271Z","lastAccessed":"2026-01-23T06:39:40.271Z"}}}}